re3data/__about__.py
re3data/__init__.py
re3data/__main__.py
re3data/_cli.py
re3data/_exceptions.py
re3data/_response.py
re3data/_serializer.py
re3data/py.typed
re3data/_client/__init__.py
re3data/_client/_async.py
re3data/_client/_sync.py
re3data/_client/base.py
re3data/_resources/__init__.py
re3data/_resources/mixins.py
re3data/_resources/repository.py
re3data/_resources/repository_list.py
python_re3data-0.10.0.dist-info/METADATA
python_re3data-0.10.0.dist-info/WHEEL
python_re3data-0.10.0.dist-info/entry_points.txt
python_re3data-0.10.0.dist-info/licenses/LICENSE
python_re3data-0.10.0.dist-info/RECORD
